smudge/__init__.py
smudge/__main__.py
smudge/__version__.py
smudge/command_line.py
smudge/utils.py
smudge-1.0.3.dist-info/LICENSE
smudge-1.0.3.dist-info/METADATA
smudge-1.0.3.dist-info/WHEEL
smudge-1.0.3.dist-info/top_level.txt
smudge-1.0.3.dist-info/RECORD
