Metadata-Version: 2.1
Name: smudge
Version: 1.0.3
Summary: Passive OS detection with dynamic signatures.
Home-page: https://github.com/activecm/smudge
Author: Dave Quartarolo
Author-email: david@activecountermeasures.com
License: UNKNOWN
Platform: UNKNOWN
Classifier: Programming Language :: Python :: 3
Classifier: Programming Language :: Python :: 3.7
Classifier: Programming Language :: Python :: 3.8
Classifier: Topic :: System :: Networking :: Monitoring
Classifier: Natural Language :: English
Classifier: License :: OSI Approved :: GNU General Public License v3 or later (GPLv3+)
Provides-Extra: dev
